[
  [
    {
      "track_id": 2,
      "class_name": "person",
      "confidence": 0.8196096420288086,
      "bbox": [
        0.3237457275390625,
        361.7059326171875,
        145.42819213867188,
        757.8536376953125
      ]
    }
  ],
  [
    {
      "track_id": 2,
      "class_name": "person",
      "confidence": 0.8165745139122009,
      "bbox": [
        0.0,
        362.0391845703125,
        147.5088348388672,
        775.50244140625
      ]
    }
  ],
  [
    {
      "track_id": 2,
      "class_name": "person",
      "confidence": 0.8635144829750061,
      "bbox": [
        0.0,
        362.2419128417969,
        150.24267578125,
        779.3189086914062
      ]
    }
  ],
  [
    {
      "track_id": 2,
      "class_name": "person",
      "confidence": 0.8828055262565613,
      "bbox": [
        1.0115543603897095,
        363.3262939453125,
        153.56199645996094,
        781.1598510742188
      ]
    }
  ],
  [
    {
      "track_id": 2,
      "class_name": "person",
      "confidence": 0.8842427134513855,
      "bbox": [
        5.020034313201904,
        362.72015380859375,
        158.6232147216797,
        783.1844482421875
      ]
    }
  ],
  [
    {
      "track_id": 2,
      "class_name": "person",
      "confidence": 0.886633574962616,
      "bbox": [
        9.365507125854492,
        362.3002014160156,
        164.09690856933594,
        785.8391723632812
      ]
    }
  ],
  [
    {
      "track_id": 2,
      "class_name": "person",
      "confidence": 0.8787497878074646,
      "bbox": [
        12.74944019317627,
        361.7904052734375,
        167.82212829589844,
        787.0133666992188
      ]
    }
  ],
  [
    {
      "track_id": 2,
      "class_name": "person",
      "confidence": 0.8765869140625,
      "bbox": [
        16.46898651123047,
        362.1805419921875,
        170.89205932617188,
        787.3336791992188
      ]
    }
  ],
  [
    {
      "track_id": 2,
      "class_name": "person",
      "confidence": 0.8723441362380981,
      "bbox": [
        20.352693557739258,
        363.0179748535156,
        173.33465576171875,
        787.4784545898438
      ]
    }
  ],
  [
    {
      "track_id": 2,
      "class_name": "person",
      "confidence": 0.8690373301506042,
      "bbox": [
        23.930953979492188,
        363.0308532714844,
        175.32290649414062,
        787.3291015625
      ]
    }
  ],
  [
    {
      "track_id": 2,
      "class_name": "person",
      "confidence": 0.8654765486717224,
      "bbox": [
        28.48958396911621,
        362.55047607421875,
        178.1547393798828,
        787.3514404296875
      ]
    }
  ],
  [
    {
      "track_id": 2,
      "class_name": "person",
      "confidence": 0.8435600399971008,
      "bbox": [
        33.21044921875,
        362.8914489746094,
        180.87826538085938,
        788.1949462890625
      ]
    }
  ],
  [
    {
      "track_id": 2,
      "class_name": "person",
      "confidence": 0.8280187845230103,
      "bbox": [
        40.03647232055664,
        363.1811218261719,
        185.89683532714844,
        788.65087890625
      ]
    }
  ],
  [
    {
      "track_id": 2,
      "class_name": "person",
      "confidence": 0.8385951519012451,
      "bbox": [
        47.04713439941406,
        364.0720520019531,
        191.66200256347656,
        788.917724609375
      ]
    }
  ],
  [
    {
      "track_id": 2,
      "class_name": "person",
      "confidence": 0.8504312634468079,
      "bbox": [
        54.586124420166016,
        364.433837890625,
        198.75840759277344,
        790.0072021484375
      ]
    }
  ],
  [
    {
      "track_id": 2,
      "class_name": "person",
      "confidence": 0.8618649244308472,
      "bbox": [
        62.19331359863281,
        365.9200134277344,
        205.2797088623047,
        789.2021484375
      ]
    }
  ],
  [
    {
      "track_id": 2,
      "class_name": "person",
      "confidence": 0.8515820503234863,
      "bbox": [
        69.9380874633789,
        368.16015625,
        212.5615997314453,
        787.7884521484375
      ]
    }
  ],
  [
    {
      "track_id": 2,
      "class_name": "person",
      "confidence": 0.8781682252883911,
      "bbox": [
        79.70271301269531,
        367.696044921875,
        223.8003387451172,
        787.4746704101562
      ]
    }
  ],
  [
    {
      "track_id": 2,
      "class_name": "person",
      "confidence": 0.8820789456367493,
      "bbox": [
        88.08043670654297,
        367.59375,
        233.88046264648438,
        787.5840454101562
      ]
    }
  ],
  [
    {
      "track_id": 2,
      "class_name": "person",
      "confidence": 0.8680713176727295,
      "bbox": [
        94.1867904663086,
        368.2227783203125,
        241.0298309326172,
        787.66845703125
      ]
    }
  ],
  [
    {
      "track_id": 2,
      "class_name": "person",
      "confidence": 0.8603835701942444,
      "bbox": [
        97.62248992919922,
        368.9515075683594,
        245.06072998046875,
        788.387451171875
      ]
    }
  ],
  [
    {
      "track_id": 2,
      "class_name": "person",
      "confidence": 0.8453299403190613,
      "bbox": [
        100.68006134033203,
        369.6115417480469,
        248.11183166503906,
        788.7609252929688
      ]
    }
  ],
  [
    {
      "track_id": 2,
      "class_name": "person",
      "confidence": 0.8508955240249634,
      "bbox": [
        102.47306060791016,
        368.5569152832031,
        250.32386779785156,
        789.8255004882812
      ]
    }
  ],
  [
    {
      "track_id": 2,
      "class_name": "person",
      "confidence": 0.8358727097511292,
      "bbox": [
        104.85911560058594,
        367.6412353515625,
        253.13002014160156,
        790.7454833984375
      ]
    }
  ],
  [
    {
      "track_id": 2,
      "class_name": "person",
      "confidence": 0.8285496830940247,
      "bbox": [
        111.26351165771484,
        367.02471923828125,
        260.1692810058594,
        790.2149658203125
      ]
    }
  ],
  [
    {
      "track_id": 2,
      "class_name": "person",
      "confidence": 0.833430826663971,
      "bbox": [
        117.2607421875,
        365.89910888671875,
        268.0679626464844,
        790.7114868164062
      ]
    }
  ],
  [
    {
      "track_id": 2,
      "class_name": "person",
      "confidence": 0.829021692276001,
      "bbox": [
        119.8472671508789,
        365.7472839355469,
        273.2000427246094,
        794.0755004882812
      ]
    }
  ],
  [
    {
      "track_id": 2,
      "class_name": "person",
      "confidence": 0.8437806963920593,
      "bbox": [
        120.5709457397461,
        365.5210266113281,
        278.81072998046875,
        804.9818115234375
      ]
    }
  ],
  [
    {
      "track_id": 2,
      "class_name": "person",
      "confidence": 0.8437172174453735,
      "bbox": [
        125.26834869384766,
        366.7886047363281,
        281.15545654296875,
        793.3956298828125
      ]
    }
  ],
  [
    {
      "track_id": 2,
      "class_name": "person",
      "confidence": 0.8819511532783508,
      "bbox": [
        133.04910278320312,
        366.9892883300781,
        283.2136535644531,
        766.5050048828125
      ]
    }
  ],
  [
    {
      "track_id": 2,
      "class_name": "person",
      "confidence": 0.8874810934066772,
      "bbox": [
        138.222900390625,
        367.92803955078125,
        287.98248291015625,
        754.6538696289062
      ]
    }
  ],
  [
    {
      "track_id": 2,
      "class_name": "person",
      "confidence": 0.8802661299705505,
      "bbox": [
        140.8417205810547,
        369.418212890625,
        291.7002868652344,
        748.6994018554688
      ]
    }
  ],
  [
    {
      "track_id": 2,
      "class_name": "person",
      "confidence": 0.9009785056114197,
      "bbox": [
        144.19296264648438,
        370.2405090332031,
        298.0001525878906,
        745.1592407226562
      ]
    }
  ],
  [
    {
      "track_id": 2,
      "class_name": "person",
      "confidence": 0.8939651846885681,
      "bbox": [
        145.2991180419922,
        371.65850830078125,
        302.518798828125,
        744.0952758789062
      ]
    }
  ],
  [
    {
      "track_id": 2,
      "class_name": "person",
      "confidence": 0.8818846940994263,
      "bbox": [
        145.76632690429688,
        373.3389587402344,
        306.1959533691406,
        743.8084716796875
      ]
    }
  ],
  [
    {
      "track_id": 2,
      "class_name": "person",
      "confidence": 0.8754279613494873,
      "bbox": [
        146.07931518554688,
        375.6944274902344,
        308.98590087890625,
        743.44580078125
      ]
    }
  ],
  [
    {
      "track_id": 2,
      "class_name": "person",
      "confidence": 0.8769009113311768,
      "bbox": [
        145.43055725097656,
        377.7026672363281,
        310.4125061035156,
        743.1492309570312
      ]
    }
  ],
  [
    {
      "track_id": 2,
      "class_name": "person",
      "confidence": 0.875007152557373,
      "bbox": [
        144.7179718017578,
        378.9501647949219,
        311.068359375,
        742.0379638671875
      ]
    }
  ],
  [
    {
      "track_id": 2,
      "class_name": "person",
      "confidence": 0.871076762676239,
      "bbox": [
        143.99478149414062,
        379.659912109375,
        311.19757080078125,
        740.7791137695312
      ]
    }
  ],
  [
    {
      "track_id": 2,
      "class_name": "person",
      "confidence": 0.8684214949607849,
      "bbox": [
        143.48081970214844,
        379.8970642089844,
        311.7325744628906,
        740.4942626953125
      ]
    }
  ],
  [
    {
      "track_id": 2,
      "class_name": "person",
      "confidence": 0.8683940768241882,
      "bbox": [
        142.8969268798828,
        380.17236328125,
        311.7445373535156,
        739.9552612304688
      ]
    }
  ],
  [
    {
      "track_id": 2,
      "class_name": "person",
      "confidence": 0.8754389882087708,
      "bbox": [
        143.57528686523438,
        381.7047424316406,
        312.1956481933594,
        740.1826782226562
      ]
    }
  ],
  [
    {
      "track_id": 2,
      "class_name": "person",
      "confidence": 0.8783032894134521,
      "bbox": [
        144.91244506835938,
        383.05255126953125,
        313.1546630859375,
        740.529296875
      ]
    }
  ],
  [
    {
      "track_id": 2,
      "class_name": "person",
      "confidence": 0.8871235847473145,
      "bbox": [
        146.3215789794922,
        382.983154296875,
        314.23968505859375,
        739.9081420898438
      ]
    }
  ],
  [
    {
      "track_id": 2,
      "class_name": "person",
      "confidence": 0.8860433101654053,
      "bbox": [
        147.99229431152344,
        383.5502624511719,
        315.404052734375,
        739.5545043945312
      ]
    }
  ],
  [
    {
      "track_id": 2,
      "class_name": "person",
      "confidence": 0.8750277757644653,
      "bbox": [
        149.49685668945312,
        384.25054931640625,
        316.6124267578125,
        739.6197509765625
      ]
    }
  ],
  [
    {
      "track_id": 2,
      "class_name": "person",
      "confidence": 0.8605419993400574,
      "bbox": [
        151.18923950195312,
        385.02447509765625,
        318.2942810058594,
        739.783447265625
      ]
    }
  ],
  [
    {
      "track_id": 2,
      "class_name": "person",
      "confidence": 0.8291121125221252,
      "bbox": [
        152.92137145996094,
        386.64007568359375,
        319.8356018066406,
        739.7311401367188
      ]
    }
  ],
  [
    {
      "track_id": 2,
      "class_name": "person",
      "confidence": 0.7874369025230408,
      "bbox": [
        154.1904754638672,
        388.0948791503906,
        320.9871826171875,
        739.2662353515625
      ]
    }
  ],
  [
    {
      "track_id": 2,
      "class_name": "person",
      "confidence": 0.7911189198493958,
      "bbox": [
        156.62005615234375,
        389.5727844238281,
        323.7230529785156,
        739.4205932617188
      ]
    }
  ],
  [
    {
      "track_id": 2,
      "class_name": "person",
      "confidence": 0.7854248285293579,
      "bbox": [
        154.8186492919922,
        390.56549072265625,
        336.0133056640625,
        773.2542724609375
      ]
    }
  ],
  [
    {
      "track_id": 2,
      "class_name": "person",
      "confidence": 0.8025213479995728,
      "bbox": [
        158.28436279296875,
        391.7469177246094,
        343.0164794921875,
        783.9713134765625
      ]
    }
  ],
  [
    {
      "track_id": 2,
      "class_name": "person",
      "confidence": 0.7550984621047974,
      "bbox": [
        160.4007568359375,
        392.2467956542969,
        353.8470153808594,
        805.156494140625
      ]
    }
  ],
  [
    {
      "track_id": 2,
      "class_name": "person",
      "confidence": 0.7304739356040955,
      "bbox": [
        158.97190856933594,
        392.9779357910156,
        363.6989440917969,
        834.78125
      ]
    }
  ],
  [
    {
      "track_id": 2,
      "class_name": "person",
      "confidence": 0.7572546601295471,
      "bbox": [
        156.56845092773438,
        391.7749938964844,
        373.38165283203125,
        866.1835327148438
      ]
    }
  ],
  [
    {
      "track_id": 2,
      "class_name": "person",
      "confidence": 0.8430449366569519,
      "bbox": [
        157.66139221191406,
        391.0359191894531,
        379.03314208984375,
        880.6152954101562
      ]
    }
  ],
  [
    {
      "track_id": 2,
      "class_name": "person",
      "confidence": 0.8492921590805054,
      "bbox": [
        160.47840881347656,
        390.978515625,
        382.9675598144531,
        886.4757080078125
      ]
    }
  ],
  [
    {
      "track_id": 2,
      "class_name": "person",
      "confidence": 0.833052933216095,
      "bbox": [
        163.0633087158203,
        391.7225646972656,
        386.2036437988281,
        891.0796508789062
      ]
    }
  ],
  [
    {
      "track_id": 2,
      "class_name": "person",
      "confidence": 0.8499642014503479,
      "bbox": [
        164.91461181640625,
        391.9227294921875,
        388.5016784667969,
        893.8916625976562
      ]
    }
  ],
  [
    {
      "track_id": 2,
      "class_name": "person",
      "confidence": 0.8368484973907471,
      "bbox": [
        167.61343383789062,
        393.13262939453125,
        389.29608154296875,
        891.3793334960938
      ]
    }
  ],
  [
    {
      "track_id": 2,
      "class_name": "person",
      "confidence": 0.8393062353134155,
      "bbox": [
        168.5922393798828,
        394.5020751953125,
        389.3475036621094,
        890.7781372070312
      ]
    }
  ],
  [
    {
      "track_id": 2,
      "class_name": "person",
      "confidence": 0.8231460452079773,
      "bbox": [
        173.25283813476562,
        395.55072021484375,
        385.08349609375,
        868.60400390625
      ]
    }
  ],
  [
    {
      "track_id": 2,
      "class_name": "person",
      "confidence": 0.8302973508834839,
      "bbox": [
        175.96652221679688,
        396.8751525878906,
        381.9210510253906,
        852.8255615234375
      ]
    }
  ],
  [
    {
      "track_id": 2,
      "class_name": "person",
      "confidence": 0.8260244727134705,
      "bbox": [
        173.82144165039062,
        398.478759765625,
        382.0026550292969,
        857.4649047851562
      ]
    }
  ],
  [
    {
      "track_id": 2,
      "class_name": "person",
      "confidence": 0.8347360491752625,
      "bbox": [
        171.66748046875,
        400.195068359375,
        379.2664794921875,
        855.5925903320312
      ]
    }
  ],
  [
    {
      "track_id": 2,
      "class_name": "person",
      "confidence": 0.8457072973251343,
      "bbox": [
        164.7031707763672,
        402.09283447265625,
        381.2645263671875,
        878.25146484375
      ]
    }
  ],
  [
    {
      "track_id": 2,
      "class_name": "person",
      "confidence": 0.8302053809165955,
      "bbox": [
        161.39950561523438,
        403.6503601074219,
        378.05889892578125,
        880.531005859375
      ]
    }
  ],
  [
    {
      "track_id": 2,
      "class_name": "person",
      "confidence": 0.8125313520431519,
      "bbox": [
        160.2642364501953,
        404.7166442871094,
        372.8426818847656,
        873.1935424804688
      ]
    }
  ],
  [
    {
      "track_id": 2,
      "class_name": "person",
      "confidence": 0.8062450289726257,
      "bbox": [
        159.13565063476562,
        405.5379638671875,
        367.7113037109375,
        865.7114868164062
      ]
    }
  ],
  [
    {
      "track_id": 2,
      "class_name": "person",
      "confidence": 0.8124818801879883,
      "bbox": [
        159.51963806152344,
        406.64764404296875,
        360.6208190917969,
        849.132568359375
      ]
    }
  ],
  [
    {
      "track_id": 2,
      "class_name": "person",
      "confidence": 0.7858522534370422,
      "bbox": [
        154.59628295898438,
        407.15277099609375,
        360.2876892089844,
        862.35302734375
      ]
    }
  ],
  [
    {
      "track_id": 2,
      "class_name": "person",
      "confidence": 0.7814057469367981,
      "bbox": [
        151.3127899169922,
        407.3181457519531,
        359.99603271484375,
        873.1591186523438
      ]
    }
  ],
  [
    {
      "track_id": 2,
      "class_name": "person",
      "confidence": 0.7831141352653503,
      "bbox": [
        150.2996063232422,
        408.23638916015625,
        358.1839904785156,
        876.69287109375
      ]
    }
  ],
  [
    {
      "track_id": 2,
      "class_name": "person",
      "confidence": 0.775142252445221,
      "bbox": [
        148.8123321533203,
        409.6256103515625,
        357.0982971191406,
        883.9528198242188
      ]
    }
  ],
  [
    {
      "track_id": 2,
      "class_name": "person",
      "confidence": 0.7587662935256958,
      "bbox": [
        147.22384643554688,
        410.20404052734375,
        355.75689697265625,
        890.7078857421875
      ]
    }
  ],
  [
    {
      "track_id": 2,
      "class_name": "person",
      "confidence": 0.786156177520752,
      "bbox": [
        144.93133544921875,
        410.72308349609375,
        356.2097473144531,
        904.8490600585938
      ]
    }
  ],
  [
    {
      "track_id": 2,
      "class_name": "person",
      "confidence": 0.7780994772911072,
      "bbox": [
        142.2345428466797,
        411.1419372558594,
        359.3577575683594,
        928.57666015625
      ]
    }
  ],
  [
    {
      "track_id": 2,
      "class_name": "person",
      "confidence": 0.7966629862785339,
      "bbox": [
        143.5491485595703,
        411.4188537597656,
        362.68218994140625,
        942.7129516601562
      ]
    }
  ],
  [
    {
      "track_id": 2,
      "class_name": "person",
      "confidence": 0.796139121055603,
      "bbox": [
        147.44500732421875,
        411.893310546875,
        366.326416015625,
        949.9315795898438
      ]
    }
  ],
  [
    {
      "track_id": 2,
      "class_name": "person",
      "confidence": 0.8018990159034729,
      "bbox": [
        152.8690643310547,
        413.0357360839844,
        371.27142333984375,
        956.00048828125
      ]
    }
  ],
  [
    {
      "track_id": 2,
      "class_name": "person",
      "confidence": 0.8266034126281738,
      "bbox": [
        156.6259307861328,
        414.0241394042969,
        374.1445617675781,
        960.7070922851562
      ]
    }
  ],
  [
    {
      "track_id": 2,
      "class_name": "person",
      "confidence": 0.8380299806594849,
      "bbox": [
        158.54441833496094,
        414.2355651855469,
        374.5288391113281,
        964.2683715820312
      ]
    }
  ],
  [
    {
      "track_id": 2,
      "class_name": "person",
      "confidence": 0.8551933765411377,
      "bbox": [
        161.8794403076172,
        415.4635925292969,
        375.3458251953125,
        966.214111328125
      ]
    }
  ],
  [
    {
      "track_id": 2,
      "class_name": "person",
      "confidence": 0.8654035925865173,
      "bbox": [
        165.3979034423828,
        416.42279052734375,
        376.0825500488281,
        967.2400512695312
      ]
    }
  ],
  [
    {
      "track_id": 2,
      "class_name": "person",
      "confidence": 0.8716916441917419,
      "bbox": [
        170.0028076171875,
        416.3261413574219,
        378.077392578125,
        967.216796875
      ]
    }
  ],
  [
    {
      "track_id": 2,
      "class_name": "person",
      "confidence": 0.8754140734672546,
      "bbox": [
        175.33709716796875,
        415.5711669921875,
        381.08154296875,
        965.97119140625
      ]
    }
  ],
  [
    {
      "track_id": 2,
      "class_name": "person",
      "confidence": 0.8926917314529419,
      "bbox": [
        180.23794555664062,
        414.6669006347656,
        384.55694580078125,
        965.1641845703125
      ]
    }
  ],
  [
    {
      "track_id": 2,
      "class_name": "person",
      "confidence": 0.8937858939170837,
      "bbox": [
        183.90821838378906,
        413.9642333984375,
        387.9002990722656,
        964.5844116210938
      ]
    }
  ],
  [
    {
      "track_id": 2,
      "class_name": "person",
      "confidence": 0.8771982192993164,
      "bbox": [
        189.47882080078125,
        413.6121520996094,
        392.9049377441406,
        962.2842407226562
      ]
    }
  ],
  [
    {
      "track_id": 2,
      "class_name": "person",
      "confidence": 0.8689390420913696,
      "bbox": [
        196.4132843017578,
        413.074462890625,
        400.35577392578125,
        961.5512084960938
      ]
    }
  ],
  [
    {
      "track_id": 2,
      "class_name": "person",
      "confidence": 0.8748223781585693,
      "bbox": [
        201.58596801757812,
        413.3476257324219,
        406.3399353027344,
        961.3844604492188
      ]
    }
  ],
  [
    {
      "track_id": 2,
      "class_name": "person",
      "confidence": 0.875049889087677,
      "bbox": [
        205.6575164794922,
        413.27252197265625,
        412.1228332519531,
        961.6539306640625
      ]
    }
  ],
  [
    {
      "track_id": 2,
      "class_name": "person",
      "confidence": 0.8526161313056946,
      "bbox": [
        210.05686950683594,
        414.2873840332031,
        419.03680419921875,
        963.4797973632812
      ]
    }
  ],
  [
    {
      "track_id": 2,
      "class_name": "person",
      "confidence": 0.835983157157898,
      "bbox": [
        213.49009704589844,
        414.68450927734375,
        427.36151123046875,
        970.5302124023438
      ]
    }
  ],
  [
    {
      "track_id": 2,
      "class_name": "person",
      "confidence": 0.7955335974693298,
      "bbox": [
        213.87889099121094,
        414.6236572265625,
        437.6876525878906,
        990.6449584960938
      ]
    }
  ],
  [
    {
      "track_id": 2,
      "class_name": "person",
      "confidence": 0.6928636431694031,
      "bbox": [
        203.0341796875,
        414.8548278808594,
        427.1322937011719,
        997.5034790039062
      ]
    }
  ],
  [
    {
      "track_id": 2,
      "class_name": "person",
      "confidence": 0.7189523577690125,
      "bbox": [
        217.05670166015625,
        415.84033203125,
        445.58612060546875,
        1000.2694702148438
      ]
    }
  ],
  [
    {
      "track_id": 2,
      "class_name": "person",
      "confidence": 0.8488989472389221,
      "bbox": [
        224.8209686279297,
        417.0773620605469,
        457.12274169921875,
        1000.8795776367188
      ]
    }
  ],
  [
    {
      "track_id": 2,
      "class_name": "person",
      "confidence": 0.8448355793952942,
      "bbox": [
        231.86837768554688,
        417.9600524902344,
        467.6822204589844,
        1001.4058227539062
      ]
    }
  ],
  [
    {
      "track_id": 2,
      "class_name": "person",
      "confidence": 0.8524787425994873,
      "bbox": [
        236.2881317138672,
        417.98681640625,
        476.0199890136719,
        1002.4417114257812
      ]
    }
  ],
  [
    {
      "track_id": 2,
      "class_name": "person",
      "confidence": 0.8633118867874146,
      "bbox": [
        239.53359985351562,
        417.8507995605469,
        483.297119140625,
        1003.6365966796875
      ]
    }
  ],
  [
    {
      "track_id": 2,
      "class_name": "person",
      "confidence": 0.8585194945335388,
      "bbox": [
        241.3311767578125,
        417.6424560546875,
        488.2936096191406,
        1003.2789306640625
      ]
    }
  ],
  [
    {
      "track_id": 2,
      "class_name": "person",
      "confidence": 0.8678045868873596,
      "bbox": [
        243.30860900878906,
        417.26055908203125,
        494.013671875,
        1003.8729858398438
      ]
    }
  ],
  [
    {
      "track_id": 2,
      "class_name": "person",
      "confidence": 0.8808600306510925,
      "bbox": [
        244.75921630859375,
        415.5680236816406,
        499.4588623046875,
        1004.1240844726562
      ]
    }
  ],
  [
    {
      "track_id": 2,
      "class_name": "person",
      "confidence": 0.8847710490226746,
      "bbox": [
        245.53884887695312,
        414.8827819824219,
        503.531005859375,
        1004.7595825195312
      ]
    }
  ],
  [
    {
      "track_id": 2,
      "class_name": "person",
      "confidence": 0.883051335811615,
      "bbox": [
        247.1571502685547,
        414.2138366699219,
        507.83331298828125,
        1004.396484375
      ]
    }
  ],
  [
    {
      "track_id": 2,
      "class_name": "person",
      "confidence": 0.8944641947746277,
      "bbox": [
        248.68223571777344,
        414.2955627441406,
        511.2011413574219,
        1003.4771728515625
      ]
    }
  ],
  [
    {
      "track_id": 2,
      "class_name": "person",
      "confidence": 0.898844838142395,
      "bbox": [
        250.28985595703125,
        414.2810363769531,
        514.0907592773438,
        1001.8797607421875
      ]
    }
  ],
  [
    {
      "track_id": 2,
      "class_name": "person",
      "confidence": 0.8986380100250244,
      "bbox": [
        253.33961486816406,
        414.9363098144531,
        519.2927856445312,
        1003.3181762695312
      ]
    }
  ],
  [
    {
      "track_id": 2,
      "class_name": "person",
      "confidence": 0.8952812552452087,
      "bbox": [
        256.385009765625,
        415.5715026855469,
        524.006591796875,
        1004.3389282226562
      ]
    }
  ],
  [
    {
      "track_id": 2,
      "class_name": "person",
      "confidence": 0.899664044380188,
      "bbox": [
        259.03106689453125,
        415.8226013183594,
        528.4657592773438,
        1005.50439453125
      ]
    }
  ],
  [
    {
      "track_id": 2,
      "class_name": "person",
      "confidence": 0.9028916954994202,
      "bbox": [
        262.1394958496094,
        415.90557861328125,
        532.6616821289062,
        1005.41357421875
      ]
    }
  ],
  [
    {
      "track_id": 2,
      "class_name": "person",
      "confidence": 0.9044299125671387,
      "bbox": [
        264.74554443359375,
        415.115966796875,
        536.5145263671875,
        1005.3269653320312
      ]
    }
  ],
  [
    {
      "track_id": 2,
      "class_name": "person",
      "confidence": 0.9019103050231934,
      "bbox": [
        266.9201965332031,
        414.63287353515625,
        540.9349975585938,
        1007.9983520507812
      ]
    }
  ],
  [
    {
      "track_id": 2,
      "class_name": "person",
      "confidence": 0.9089680314064026,
      "bbox": [
        270.134033203125,
        413.6321105957031,
        545.4291381835938,
        1008.42236328125
      ]
    }
  ],
  [
    {
      "track_id": 2,
      "class_name": "person",
      "confidence": 0.9177889823913574,
      "bbox": [
        274.4464111328125,
        414.39190673828125,
        550.110595703125,
        1008.0274047851562
      ]
    }
  ],
  [
    {
      "track_id": 2,
      "class_name": "person",
      "confidence": 0.9243251085281372,
      "bbox": [
        277.9067077636719,
        412.4389343261719,
        555.47314453125,
        1007.58740234375
      ]
    }
  ],
  [
    {
      "track_id": 2,
      "class_name": "person",
      "confidence": 0.9203924536705017,
      "bbox": [
        280.72845458984375,
        412.86029052734375,
        559.1651611328125,
        1007.1441040039062
      ]
    }
  ],
  [
    {
      "track_id": 2,
      "class_name": "person",
      "confidence": 0.9278527498245239,
      "bbox": [
        284.5447692871094,
        413.24871826171875,
        564.7418212890625,
        1007.3950805664062
      ]
    }
  ],
  [
    {
      "track_id": 2,
      "class_name": "person",
      "confidence": 0.9296482801437378,
      "bbox": [
        286.23724365234375,
        414.4189453125,
        567.9163818359375,
        1007.8390502929688
      ]
    }
  ],
  [
    {
      "track_id": 2,
      "class_name": "person",
      "confidence": 0.9267670512199402,
      "bbox": [
        288.0202331542969,
        414.90240478515625,
        572.1495361328125,
        1008.5283813476562
      ]
    }
  ],
  [
    {
      "track_id": 2,
      "class_name": "person",
      "confidence": 0.9097990989685059,
      "bbox": [
        292.21923828125,
        414.6667785644531,
        579.1419067382812,
        1009.0950927734375
      ]
    }
  ],
  [
    {
      "track_id": 2,
      "class_name": "person",
      "confidence": 0.870812177658081,
      "bbox": [
        297.4421691894531,
        413.1252136230469,
        582.71630859375,
        997.6737060546875
      ]
    }
  ],
  [
    {
      "track_id": 2,
      "class_name": "person",
      "confidence": 0.8601465225219727,
      "bbox": [
        301.627197265625,
        413.71697998046875,
        586.1295166015625,
        989.0131225585938
      ]
    }
  ],
  [
    {
      "track_id": 2,
      "class_name": "person",
      "confidence": 0.8605721592903137,
      "bbox": [
        305.0067443847656,
        414.96807861328125,
        590.8936157226562,
        983.6597290039062
      ]
    }
  ],
  [
    {
      "track_id": 2,
      "class_name": "person",
      "confidence": 0.8590103387832642,
      "bbox": [
        304.5570983886719,
        415.94293212890625,
        593.9714965820312,
        983.6940307617188
      ]
    }
  ],
  [
    {
      "track_id": 2,
      "class_name": "person",
      "confidence": 0.8608130216598511,
      "bbox": [
        301.2679138183594,
        416.380615234375,
        595.9469604492188,
        988.6509399414062
      ]
    }
  ],
  [
    {
      "track_id": 2,
      "class_name": "person",
      "confidence": 0.8574673533439636,
      "bbox": [
        304.207275390625,
        416.977294921875,
        593.9122314453125,
        970.9105834960938
      ]
    }
  ],
  [
    {
      "track_id": 2,
      "class_name": "person",
      "confidence": 0.8716398477554321,
      "bbox": [
        309.1761779785156,
        418.0414123535156,
        588.9608154296875,
        941.8737182617188
      ]
    }
  ],
  [
    {
      "track_id": 2,
      "class_name": "person",
      "confidence": 0.8842364549636841,
      "bbox": [
        311.0734558105469,
        420.094970703125,
        587.1077270507812,
        926.3417358398438
      ]
    }
  ],
  [
    {
      "track_id": 2,
      "class_name": "person",
      "confidence": 0.882564127445221,
      "bbox": [
        309.34228515625,
        421.6374206542969,
        586.9154052734375,
        921.6758422851562
      ]
    }
  ],
  [
    {
      "track_id": 2,
      "class_name": "person",
      "confidence": 0.8826794624328613,
      "bbox": [
        307.302490234375,
        422.6126403808594,
        587.8436889648438,
        919.852294921875
      ]
    }
  ],
  [
    {
      "track_id": 2,
      "class_name": "person",
      "confidence": 0.8825582265853882,
      "bbox": [
        305.0269775390625,
        423.3024597167969,
        589.8013305664062,
        920.6157836914062
      ]
    }
  ],
  [
    {
      "track_id": 2,
      "class_name": "person",
      "confidence": 0.8893895149230957,
      "bbox": [
        301.7025146484375,
        424.2301025390625,
        589.984130859375,
        921.580810546875
      ]
    }
  ],
  [
    {
      "track_id": 2,
      "class_name": "person",
      "confidence": 0.8799437880516052,
      "bbox": [
        298.3934631347656,
        425.9739074707031,
        590.9898681640625,
        925.730224609375
      ]
    }
  ],
  [
    {
      "track_id": 2,
      "class_name": "person",
      "confidence": 0.8934510350227356,
      "bbox": [
        293.14044189453125,
        428.1876220703125,
        590.8868408203125,
        933.8597412109375
      ]
    }
  ],
  [
    {
      "track_id": 2,
      "class_name": "person",
      "confidence": 0.8918718099594116,
      "bbox": [
        289.95770263671875,
        430.5744323730469,
        588.6288452148438,
        935.060791015625
      ]
    }
  ],
  [
    {
      "track_id": 2,
      "class_name": "person",
      "confidence": 0.8927160501480103,
      "bbox": [
        285.5879821777344,
        432.84478759765625,
        586.7731323242188,
        939.5864868164062
      ]
    }
  ],
  [
    {
      "track_id": 2,
      "class_name": "person",
      "confidence": 0.8777703642845154,
      "bbox": [
        279.0851745605469,
        434.8496398925781,
        581.3114624023438,
        942.6524658203125
      ]
    }
  ],
  [
    {
      "track_id": 2,
      "class_name": "person",
      "confidence": 0.870983898639679,
      "bbox": [
        270.5146789550781,
        437.5398254394531,
        576.881591796875,
        953.898193359375
      ]
    }
  ],
  [
    {
      "track_id": 2,
      "class_name": "person",
      "confidence": 0.8666747212409973,
      "bbox": [
        261.4444885253906,
        439.91748046875,
        569.7766723632812,
        962.397705078125
      ]
    }
  ],
  [
    {
      "track_id": 2,
      "class_name": "person",
      "confidence": 0.8464824557304382,
      "bbox": [
        255.92066955566406,
        442.0950927734375,
        560.2611694335938,
        960.17431640625
      ]
    }
  ],
  [
    {
      "track_id": 2,
      "class_name": "person",
      "confidence": 0.8493462204933167,
      "bbox": [
        252.01040649414062,
        444.7510070800781,
        550.6627807617188,
        954.4066772460938
      ]
    }
  ],
  [
    {
      "track_id": 2,
      "class_name": "person",
      "confidence": 0.810593843460083,
      "bbox": [
        233.7661590576172,
        445.7358093261719,
        529.4134521484375,
        959.0563354492188
      ]
    }
  ],
  [
    {
      "track_id": 2,
      "class_name": "person",
      "confidence": 0.8429935574531555,
      "bbox": [
        233.03578186035156,
        446.7366027832031,
        531.1233520507812,
        968.0087280273438
      ]
    }
  ],
  [
    {
      "track_id": 2,
      "class_name": "person",
      "confidence": 0.8503590822219849,
      "bbox": [
        227.32553100585938,
        451.32318115234375,
        524.337158203125,
        976.8960571289062
      ]
    }
  ],
  [
    {
      "track_id": 2,
      "class_name": "person",
      "confidence": 0.8327189087867737,
      "bbox": [
        221.47836303710938,
        454.531982421875,
        512.1868286132812,
        976.3925170898438
      ]
    }
  ],
  [
    {
      "track_id": 2,
      "class_name": "person",
      "confidence": 0.8478789925575256,
      "bbox": [
        215.6060791015625,
        456.4188537597656,
        502.38287353515625,
        979.901123046875
      ]
    }
  ],
  [
    {
      "track_id": 2,
      "class_name": "person",
      "confidence": 0.8651952743530273,
      "bbox": [
        211.62222290039062,
        458.6517639160156,
        494.52642822265625,
        984.1422119140625
      ]
    }
  ],
  [
    {
      "track_id": 2,
      "class_name": "person",
      "confidence": 0.8756909370422363,
      "bbox": [
        208.6918487548828,
        459.9320373535156,
        491.2517395019531,
        994.1196899414062
      ]
    }
  ],
  [
    {
      "track_id": 2,
      "class_name": "person",
      "confidence": 0.8760069012641907,
      "bbox": [
        208.53912353515625,
        461.53656005859375,
        489.88995361328125,
        1002.1470947265625
      ]
    }
  ],
  [
    {
      "track_id": 2,
      "class_name": "person",
      "confidence": 0.8632608652114868,
      "bbox": [
        206.1160888671875,
        463.9591979980469,
        492.63323974609375,
        1024.252685546875
      ]
    }
  ],
  [
    {
      "track_id": 2,
      "class_name": "person",
      "confidence": 0.8568533658981323,
      "bbox": [
        204.57571411132812,
        464.6816711425781,
        498.9836120605469,
        1051.6046142578125
      ]
    }
  ],
  [
    {
      "track_id": 2,
      "class_name": "person",
      "confidence": 0.8291468620300293,
      "bbox": [
        199.2545166015625,
        468.42156982421875,
        509.71588134765625,
        1101.797119140625
      ]
    }
  ],
  [
    {
      "track_id": 2,
      "class_name": "person",
      "confidence": 0.8740167021751404,
      "bbox": [
        195.19859313964844,
        472.51165771484375,
        518.8189697265625,
        1149.2845458984375
      ]
    }
  ],
  [
    {
      "track_id": 2,
      "class_name": "person",
      "confidence": 0.8611530661582947,
      "bbox": [
        199.0251007080078,
        480.2068176269531,
        521.41552734375,
        1168.8944091796875
      ]
    }
  ],
  [
    {
      "track_id": 2,
      "class_name": "person",
      "confidence": 0.8658701181411743,
      "bbox": [
        205.6587371826172,
        486.1884765625,
        521.5620727539062,
        1173.317626953125
      ]
    }
  ],
  [
    {
      "track_id": 2,
      "class_name": "person",
      "confidence": 0.8626471757888794,
      "bbox": [
        217.170654296875,
        492.9858093261719,
        517.993408203125,
        1154.0960693359375
      ]
    }
  ],
  [
    {
      "track_id": 2,
      "class_name": "person",
      "confidence": 0.8676494359970093,
      "bbox": [
        223.0314178466797,
        502.654541015625,
        519.6423950195312,
        1161.6854248046875
      ]
    }
  ],
  [
    {
      "track_id": 2,
      "class_name": "person",
      "confidence": 0.8662230372428894,
      "bbox": [
        228.5493927001953,
        511.7732849121094,
        522.4451293945312,
        1171.7808837890625
      ]
    }
  ],
  [
    {
      "track_id": 2,
      "class_name": "person",
      "confidence": 0.8730244040489197,
      "bbox": [
        236.0063018798828,
        521.8394775390625,
        525.5143432617188,
        1178.935791015625
      ]
    }
  ],
  [
    {
      "track_id": 2,
      "class_name": "person",
      "confidence": 0.8687449097633362,
      "bbox": [
        242.4410400390625,
        531.1060180664062,
        526.121337890625,
        1180.77392578125
      ]
    }
  ],
  [
    {
      "track_id": 2,
      "class_name": "person",
      "confidence": 0.8592562675476074,
      "bbox": [
        250.12948608398438,
        549.980224609375,
        524.4313354492188,
        1181.485107421875
      ]
    }
  ],
  [
    {
      "track_id": 2,
      "class_name": "person",
      "confidence": 0.8713195323944092,
      "bbox": [
        256.7444152832031,
        564.4038696289062,
        524.3658447265625,
        1183.691650390625
      ]
    }
  ],
  [
    {
      "track_id": 2,
      "class_name": "person",
      "confidence": 0.8688191771507263,
      "bbox": [
        263.10260009765625,
        579.2520141601562,
        523.7406005859375,
        1184.555419921875
      ]
    }
  ],
  [
    {
      "track_id": 2,
      "class_name": "person",
      "confidence": 0.8747186660766602,
      "bbox": [
        268.2561340332031,
        591.6494750976562,
        522.3742065429688,
        1183.3616943359375
      ]
    }
  ],
  [
    {
      "track_id": 2,
      "class_name": "person",
      "confidence": 0.8753178119659424,
      "bbox": [
        272.849365234375,
        602.1643676757812,
        521.6847534179688,
        1183.142333984375
      ]
    }
  ],
  [
    {
      "track_id": 2,
      "class_name": "person",
      "confidence": 0.8730642199516296,
      "bbox": [
        276.6678466796875,
        613.5108642578125,
        520.3843994140625,
        1183.5888671875
      ]
    }
  ],
  [
    {
      "track_id": 2,
      "class_name": "person",
      "confidence": 0.8799476027488708,
      "bbox": [
        280.1174011230469,
        624.6687622070312,
        518.7083129882812,
        1182.9697265625
      ]
    }
  ],
  [
    {
      "track_id": 2,
      "class_name": "person",
      "confidence": 0.871146559715271,
      "bbox": [
        282.83489990234375,
        634.874267578125,
        517.4461059570312,
        1183.607177734375
      ]
    }
  ],
  [
    {
      "track_id": 2,
      "class_name": "person",
      "confidence": 0.8773505091667175,
      "bbox": [
        285.902099609375,
        645.5750122070312,
        516.0056762695312,
        1182.6160888671875
      ]
    }
  ],
  [
    {
      "track_id": 2,
      "class_name": "person",
      "confidence": 0.8748596906661987,
      "bbox": [
        288.9654846191406,
        655.7596435546875,
        514.3558959960938,
        1179.6229248046875
      ]
    }
  ],
  [
    {
      "track_id": 2,
      "class_name": "person",
      "confidence": 0.8661794662475586,
      "bbox": [
        292.0245666503906,
        664.3133544921875,
        513.2572631835938,
        1175.3994140625
      ]
    }
  ],
  [
    {
      "track_id": 2,
      "class_name": "person",
      "confidence": 0.8748927116394043,
      "bbox": [
        293.9337463378906,
        669.967529296875,
        512.6890869140625,
        1171.761962890625
      ]
    }
  ],
  [
    {
      "track_id": 2,
      "class_name": "person",
      "confidence": 0.8729032278060913,
      "bbox": [
        295.23974609375,
        674.9413452148438,
        512.0445556640625,
        1168.5360107421875
      ]
    }
  ],
  [
    {
      "track_id": 2,
      "class_name": "person",
      "confidence": 0.8694714307785034,
      "bbox": [
        297.4407958984375,
        679.3069458007812,
        511.7568359375,
        1162.3607177734375
      ]
    }
  ],
  [
    {
      "track_id": 2,
      "class_name": "person",
      "confidence": 0.8674393892288208,
      "bbox": [
        299.1031494140625,
        682.483642578125,
        511.5007629394531,
        1155.33642578125
      ]
    }
  ],
  [
    {
      "track_id": 2,
      "class_name": "person",
      "confidence": 0.8742422461509705,
      "bbox": [
        300.65362548828125,
        684.657958984375,
        512.429443359375,
        1149.54150390625
      ]
    }
  ],
  [
    {
      "track_id": 2,
      "class_name": "person",
      "confidence": 0.869191586971283,
      "bbox": [
        302.41986083984375,
        686.8090209960938,
        513.8833618164062,
        1144.2342529296875
      ]
    }
  ],
  [
    {
      "track_id": 2,
      "class_name": "person",
      "confidence": 0.8777335286140442,
      "bbox": [
        304.60687255859375,
        689.0427856445312,
        516.01025390625,
        1138.3336181640625
      ]
    }
  ],
  [
    {
      "track_id": 2,
      "class_name": "person",
      "confidence": 0.8787317872047424,
      "bbox": [
        306.4109802246094,
        690.9050903320312,
        517.4769897460938,
        1130.911376953125
      ]
    }
  ],
  [
    {
      "track_id": 2,
      "class_name": "person",
      "confidence": 0.8810830116271973,
      "bbox": [
        308.4416809082031,
        692.63720703125,
        519.74853515625,
        1123.845458984375
      ]
    }
  ],
  [
    {
      "track_id": 2,
      "class_name": "person",
      "confidence": 0.8845185041427612,
      "bbox": [
        309.6953430175781,
        693.6954345703125,
        522.063720703125,
        1117.6370849609375
      ]
    }
  ],
  [
    {
      "track_id": 2,
      "class_name": "person",
      "confidence": 0.8789888620376587,
      "bbox": [
        310.5809326171875,
        694.3370361328125,
        524.8831176757812,
        1112.8790283203125
      ]
    }
  ],
  [
    {
      "track_id": 2,
      "class_name": "person",
      "confidence": 0.8878142833709717,
      "bbox": [
        310.07403564453125,
        693.8485717773438,
        527.4183349609375,
        1109.7991943359375
      ]
    }
  ],
  [
    {
      "track_id": 2,
      "class_name": "person",
      "confidence": 0.889570415019989,
      "bbox": [
        309.5158996582031,
        693.5706787109375,
        529.1788330078125,
        1105.311279296875
      ]
    }
  ],
  [
    {
      "track_id": 2,
      "class_name": "person",
      "confidence": 0.8843421339988708,
      "bbox": [
        308.7952575683594,
        692.3838500976562,
        531.237060546875,
        1101.0252685546875
      ]
    }
  ],
  [
    {
      "track_id": 2,
      "class_name": "person",
      "confidence": 0.8791975975036621,
      "bbox": [
        308.665771484375,
        689.7695922851562,
        534.546142578125,
        1097.0162353515625
      ]
    }
  ],
  [
    {
      "track_id": 2,
      "class_name": "person",
      "confidence": 0.8769790530204773,
      "bbox": [
        307.8896789550781,
        686.07568359375,
        537.8751220703125,
        1093.995849609375
      ]
    }
  ],
  [
    {
      "track_id": 2,
      "class_name": "person",
      "confidence": 0.8747692108154297,
      "bbox": [
        305.97406005859375,
        680.5906982421875,
        540.6402587890625,
        1090.918701171875
      ]
    }
  ],
  [
    {
      "track_id": 2,
      "class_name": "person",
      "confidence": 0.8633010983467102,
      "bbox": [
        303.1236572265625,
        674.2557373046875,
        542.2657470703125,
        1087.2257080078125
      ]
    }
  ],
  [
    {
      "track_id": 2,
      "class_name": "person",
      "confidence": 0.8699469566345215,
      "bbox": [
        300.3186340332031,
        666.37451171875,
        545.1631469726562,
        1084.9422607421875
      ]
    }
  ]
]